LocalNote/__init__.py
LocalNote/controllers.py
LocalNote/exception.py
LocalNote/main.py
LocalNote/evernoteapi/__init__.py
LocalNote/evernoteapi/controller.py
LocalNote/evernoteapi/oauth.py
LocalNote/evernoteapi/oauth2.py
LocalNote/evernoteapi/storage.py
LocalNote/local/__init__.py
LocalNote/local/enml2.dtd
LocalNote/local/enml2_dtd.py
LocalNote/local/storage.py
LocalNote/local/tools.py
LocalNote-1.0.14.dist-info/DESCRIPTION.rst
LocalNote-1.0.14.dist-info/METADATA
LocalNote-1.0.14.dist-info/RECORD
LocalNote-1.0.14.dist-info/WHEEL
LocalNote-1.0.14.dist-info/entry_points.txt
LocalNote-1.0.14.dist-info/metadata.json
LocalNote-1.0.14.dist-info/top_level.txt
