Metadata-Version: 2.0
Name: LocalNote
Version: 1.0.14
Summary: LocalNote让你能够像使用本地文件一样使用印象笔记，支持markdown语法。Use your evernote like local file system in all platforms (markdown supported)
Home-page: https://github.com/littlecodersh/LocalNote
Author: LittleCoder
Author-email: i7meavnktqegm1b@qq.com
License: MIT
Keywords: evernote local markdown python
Platform: UNKNOWN
Classifier: Development Status :: 3 - Alpha
Classifier: Intended Audience :: Developers
Classifier: Topic :: Software Development :: Libraries :: Python Modules
Classifier: License :: OSI Approved :: MIT License
Classifier: Programming Language :: Python :: 2.7
Requires-Dist: chardet
Requires-Dist: evernote
Requires-Dist: html2text
Requires-Dist: lxml
Requires-Dist: markdown
Requires-Dist: requests
